turbo_ml/__init__.py
turbo_ml/__main__.py
turbo_ml/algorithms/__init__.py
turbo_ml/algorithms/ada_boost.py
turbo_ml/algorithms/cat_boost.py
turbo_ml/algorithms/decision_tree_classifier.py
turbo_ml/algorithms/g_boost.py
turbo_ml/algorithms/neural_network.py
turbo_ml/algorithms/other_algorithms.py
turbo_ml/algorithms/random_guessing.py
turbo_ml/algorithms/xg_boost.py
turbo_ml/base/__init__.py
turbo_ml/base/evaluation/__init__.py
turbo_ml/base/evaluation/evaluator.py
turbo_ml/base/model.py
turbo_ml/base/preprocess.py
turbo_ml/base/process.py
turbo_ml/base/workflow.py
turbo_ml/interface/__init__.py
turbo_ml/interface/items.py
turbo_ml/interface/tutorial.py
turbo_ml/interface/welcome.py
turbo_ml/meta_learning/__init__.py
turbo_ml/meta_learning/hpo/__init__.py
turbo_ml/meta_learning/hpo/hyperparameter_tuning.py
turbo_ml/meta_learning/hpo/hyperparameters.json
turbo_ml/meta_learning/hpo/sklearn_hyperparameters.json
turbo_ml/meta_learning/hpo/sklearn_param_extraction.py
turbo_ml/meta_learning/meta_model/__init__.py
turbo_ml/meta_learning/meta_model/as_meta_model.py
turbo_ml/meta_learning/meta_model/dataset_preparations.py
turbo_ml/meta_learning/meta_model/load_and_dump.py
turbo_ml/meta_learning/meta_model/meta_model_search.py
turbo_ml/meta_learning/meta_model/model.pth
turbo_ml/meta_learning/model_prediction/__init__.py
turbo_ml/meta_learning/model_prediction/available.py
turbo_ml/meta_learning/model_prediction/dataset_characteristics.py
turbo_ml/meta_learning/model_prediction/model_prediction.py
turbo_ml/meta_learning/model_prediction/preprocessing_forecast.py
turbo_ml/preprocessing/__init__.py
turbo_ml/preprocessing/combined.py
turbo_ml/preprocessing/label_encoder.py
turbo_ml/preprocessing/nan_imputer.py
turbo_ml/preprocessing/normalizer.py
turbo_ml/preprocessing/one_hot_encoder.py
turbo_ml/preprocessing/sota.py
turbo_ml/preprocessing/standardizer.py
turbo_ml/preprocessing/variance_selector.py
turbo_ml/turbo_ml_experimental.py
turbo_ml/turboml.py
turbo_ml-0.1.3.dist-info/LICENSE
turbo_ml-0.1.3.dist-info/METADATA
turbo_ml-0.1.3.dist-info/WHEEL
turbo_ml-0.1.3.dist-info/RECORD
