Metadata-Version: 2.1
Name: turbo-ml
Version: 0.1.3
Summary: Auto ML library for automated model selection using pre-trained neural networks
Author: Dawid Siera
Author-email: dawid.siera@gmail.com
Requires-Python: >=3.10,<4.0
Classifier: Programming Language :: Python :: 3
Classifier: Programming Language :: Python :: 3.10
Classifier: Programming Language :: Python :: 3.11
Classifier: Programming Language :: Python :: 3.12
Requires-Dist: certifi (>=2021.5.30,<2022.0.0)
Requires-Dist: numpy (>=2.0.0,<3.0.0)
Requires-Dist: optuna (>=2.9.1,<3.0.0)
Requires-Dist: pandas (>=2.0.3,<3.0.0)
Requires-Dist: requests (>=2.26.0,<3.0.0)
Requires-Dist: scikit-learn (>=1.0.0,<2.0.0)
Requires-Dist: torch (>=2.0.0,<3.0.0)
Requires-Dist: xgboost (>=2.0.0,<3.0.0)
